yodine/__init__.py
yodine/__main__.py
yodine/editor.py
yodine/game.py
yodine/gamedefs.py
yodine/launcher.py
yodine/main.py
yodine/version.py
yodine/core/__init__.py
yodine/core/advjson.py
yodine/core/entity.py
yodine/core/extension.py
yodine/core/network.py
yodine/core/trig.py
yodine/core/vector.py
yodine/utils/__init__.py
yodine/utils/plugin_init.py
Yodine-0.3.2.dist-info/METADATA
Yodine-0.3.2.dist-info/WHEEL
Yodine-0.3.2.dist-info/top_level.txt
Yodine-0.3.2.dist-info/RECORD
