Metadata-Version: 2.1
Name: Yodine
Version: 0.3.2
Summary: A simple pyglet-powered 2D game engine, with simple multiplayer support.
Home-page: UNKNOWN
Author: Gustavo6046
Author-email: UNKNOWN
License: MIT
Platform: UNKNOWN
Classifier: Programming Language :: Python
Classifier: Programming Language :: Python :: 3.5
Requires-Dist: pyglet (>=1.4.1)
Requires-Dist: setuptools (>=39.0.1)
Requires-Dist: simplejson (>=3.16.0)
Requires-Dist: trio (>=0.11.0)
Requires-Dist: typing (>=3.6.6)
